Workbook

Sheet Assumptions
A1: Parameter | B1: Value | C1: Units | D1: Notes / Source
A2: token_symbol | B2: ECHO | C2: text | D2: https://localhost/internal-simulation-assumptions
A3: payment_token_symbol | B3: USDC | C3: text | D3: https://localhost/internal-simulation-assumptions
A4: stake_amount | B4: 1000 | C4: tokens | D4: https://localhost/internal-simulation-assumptions
A5: min_stake | B5: 100 | C5: tokens | D5: https://localhost/internal-simulation-assumptions
A6: reward_campaign_funding | B6: 5000 | C6: tokens | D6: https://localhost/internal-simulation-assumptions
A7: reward_claim_amount | B7: 500 | C7: tokens | D7: https://localhost/internal-simulation-assumptions
A8: reward_campaign_max_total | B8: 10000 | C8: tokens | D8: https://localhost/internal-simulation-assumptions
A9: vesting_total | B9: 12000 | C9: tokens | D9: https://localhost/internal-simulation-assumptions
A10: vesting_release_amount | B10: 1000 | C10: tokens | D10: https://localhost/internal-simulation-assumptions
A11: marketplace_sale_price | B11: 1000 | C11: USDC | D11: https://localhost/internal-simulation-assumptions
A12: treasury_fee_bps | B12: 500 | C12: bps | D12: https://localhost/internal-simulation-assumptions
A13: devfund_fee_bps | B13: 250 | C13: bps | D13: https://localhost/internal-simulation-assumptions
A14: union_fee_bps | B14: 500 | C14: bps | D14: https://localhost/internal-simulation-assumptions
A15: note | B15: Fork blocked: system-configuration NULL object crash | C15: text | D15: https://localhost/internal-simulation-assumptions
A16: total_fee_bps | B16: =B11+B12+B13 | C16: bps | D16: https://localhost/internal-simulation-assumptions
A17: seller_bps | B17: =10000-B14 | C17: bps | D17: https://localhost/internal-simulation-assumptions
A18: seller_payout | B18: =B10*B15/10000 | C18: USDC | D18: https://localhost/internal-simulation-assumptions
A19: treasury_payout | B19: =B10*B11/10000 | C19: USDC | D19: https://localhost/internal-simulation-assumptions
A20: devfund_payout | B20: =B10*B12/10000 | C20: USDC | D20: https://localhost/internal-simulation-assumptions
A21: union_payout | B21: =B10*B13/10000 | C21: USDC | D21: https://localhost/internal-simulation-assumptions

Sheet Actors
A1: Actor | B1: Role | C1: Starting Token Balance | D1: Starting USDC Balance | E1: Starting Pending Payments | F1: Notes
A2: founder/admin | B2: governance + config | C2: 100000 | D2: 0 | E2: 0 | F2: modelled
A3: operator | B3: ops + rewards | C3: 10000 | D3: 0 | E3: 0 | F3: modelled
A4: participant | B4: staking/claim | C4: 2000 | D4: 0 | E4: 0 | F4: modelled
A5: collaborator | B5: rights/usage | C5: 0 | D5: 0 | E5: 0 | F5: modelled
A6: seller | B6: commercialization | C6: 0 | D6: 0 | E6: 0 | F6: modelled
A7: buyer | B7: purchase | C7: 0 | D7: 2000 | E7: 0 | F7: modelled
A8: treasury/payee | B8: protocol revenue | C8: 0 | D8: 0 | E8: 0 | F8: modelled
A9: emergency/admin | B9: emergency authority | C9: 0 | D9: 0 | E9: 0 | F9: modelled

Sheet Scenarios
A1: ID | B1: Scenario | C1: Primary Workflow / Route | D1: Starting State | E1: Expected Outcome | F1: Fork Required | G1: Fork Status | H1: Notes
A2: 1 | B2: staking + delegation + reward campaign setup | C2: stake-and-delegate, create-reward-campaign | D2: stake=0, campaign funding=0 | E2: stake+campaign created | F2: yes | G2: blocked | H2: modelled in Economics
A3: 2 | B3: reward claim with funding | C3: claim-reward-campaign | D3: campaign funded | E3: claim succeeds | F3: yes | G3: blocked | H3: modelled
A4: 3 | B4: reward claim without funding | C4: claim-reward-campaign | D4: campaign unfunded | E4: honest block | F4: yes | G4: blocked | H4: modelled
A5: 4 | B5: vesting creation/release/revoke | C5: create-beneficiary-vesting, release-beneficiary-vesting | D5: no schedule | E5: schedule exists + release | F5: yes | G5: blocked | H5: modelled
A6: 5 | B6: marketplace payout accumulation | C6: purchase-marketplace-asset | D6: listing active | E6: pending balances increase | F6: yes | G6: blocked | H6: modelled
A7: 6 | B7: marketplace withdrawal | C7: withdraw-marketplace-payments | D7: pending > 0 | E7: pending cleared | F7: yes | G7: blocked | H7: modelled
A8: 7 | B8: participant activation incentive flow | C8: participant-activation-flow | D8: stake + campaign + claim | E8: claim + vesting | F8: yes | G8: blocked | H8: modelled

Sheet Economics
A1: Scenario | B1: Stake Before | C1: Stake After | D1: Stake Delta | E1: Campaign Funding Before | F1: Campaign Funding After | G1: Funding Delta | H1: Claimable Before | I1: Claimable After | J1: Claim Delta | K1: Pending Before | L1: Pending After | M1: Pending Delta | N1: Vesting Total Before | O1: Vesting Total After | P1: Vesting Total Delta | Q1: Vesting Released Before | R1: Vesting Released After | S1: Vesting Released Delta | T1: Treasury Balance Before | U1: Treasury Balance After | V1: Treasury Delta | W1: Seller Balance Before | X1: Seller Balance After | Y1: Seller Delta
A2: 1. Stake + campaign setup | B2: 0 | C2: =Assumptions!B3 | D2: =C2-B2 | E2: 0 | F2: =Assumptions!B5 | G2: =F2-E2 | H2: 0 | I2: 0 | J2: =I2-H2 | K2: 0 | L2: 0 | M2: =L2-K2 | N2: 0 | O2: 0 | P2: =O2-N2 | Q2: 0 | R2: 0 | S2: =R2-Q2 | T2: 0 | U2: 0 | V2: =U2-T2 | W2: 0 | X2: 0 | Y2: =X2-W2
A3: 2. Claim with funding | B3: =Assumptions!B3 | C3: =Assumptions!B3 | D3: =C3-B3 | E3: =Assumptions!B5 | F3: =Assumptions!B5-Assumptions!B6 | G3: =F3-E3 | H3: =Assumptions!B6 | I3: 0 | J3: =I3-H3 | K3: 0 | L3: 0 | M3: =L3-K3 | N3: 0 | O3: 0 | P3: =O3-N3 | Q3: 0 | R3: 0 | S3: =R3-Q3 | T3: 0 | U3: 0 | V3: =U3-T3 | W3: 0 | X3: 0 | Y3: =X3-W3
A4: 3. Claim without funding (blocked) | B4: =Assumptions!B3 | C4: =Assumptions!B3 | D4: =C4-B4 | E4: 0 | F4: 0 | G4: =F4-E4 | H4: =Assumptions!B6 | I4: =Assumptions!B6 | J4: =I4-H4 | K4: 0 | L4: 0 | M4: =L4-K4 | N4: 0 | O4: 0 | P4: =O4-N4 | Q4: 0 | R4: 0 | S4: =R4-Q4 | T4: 0 | U4: 0 | V4: =U4-T4 | W4: 0 | X4: 0 | Y4: =X4-W4
A5: 4. Vesting create + release | B5: 0 | C5: 0 | D5: =C5-B5 | E5: 0 | F5: 0 | G5: =F5-E5 | H5: 0 | I5: 0 | J5: =I5-H5 | K5: 0 | L5: 0 | M5: =L5-K5 | N5: 0 | O5: =Assumptions!B8 | P5: =O5-N5 | Q5: 0 | R5: =Assumptions!B9 | S5: =R5-Q5 | T5: 0 | U5: 0 | V5: =U5-T5 | W5: 0 | X5: 0 | Y5: =X5-W5
A6: 5. Marketplace sale pending accrual | B6: 0 | C6: 0 | D6: =C6-B6 | E6: 0 | F6: 0 | G6: =F6-E6 | H6: 0 | I6: 0 | J6: =I6-H6 | K6: 0 | L6: =Assumptions!B16 | M6: =L6-K6 | N6: 0 | O6: 0 | P6: =O6-N6 | Q6: 0 | R6: 0 | S6: =R6-Q6 | T6: 0 | U6: =Assumptions!B17 | V6: =U6-T6 | W6: 0 | X6: 0 | Y6: =X6-W6
A7: 6. Withdrawal clears pending | B7: 0 | C7: 0 | D7: =C7-B7 | E7: 0 | F7: 0 | G7: =F7-E7 | H7: 0 | I7: 0 | J7: =I7-H7 | K7: =Assumptions!B16 | L7: 0 | M7: =L7-K7 | N7: 0 | O7: 0 | P7: =O7-N7 | Q7: 0 | R7: 0 | S7: =R7-Q7 | T7: =Assumptions!B17 | U7: =Assumptions!B17 | V7: =U7-T7 | W7: 0 | X7: =Assumptions!B16 | Y7: =X7-W7
A8: 7. Participant activation package | B8: 0 | C8: =Assumptions!B3 | D8: =C8-B8 | E8: =Assumptions!B5 | F8: =Assumptions!B5-Assumptions!B6 | G8: =F8-E8 | H8: =Assumptions!B6 | I8: 0 | J8: =I8-H8 | K8: 0 | L8: 0 | M8: =L8-K8 | N8: 0 | O8: =Assumptions!B8 | P8: =O8-N8 | Q8: 0 | R8: =Assumptions!B9 | S8: =R8-Q8 | T8: 0 | U8: 0 | V8: =U8-T8 | W8: 0 | X8: 0 | Y8: =X8-W8

Sheet Findings
A1: Finding | B1: Scenario | C1: Type | D1: Status | E1: Notes
A2: Claim blocked when campaign unfunded | B2: 3 | C2: honest block | D2: modelled | E2: matches claim-reward-campaign normalization
A3: Withdrawal blocked when pending = 0 | B3: 6 | C3: honest block | D3: modelled | E3: withdraw-marketplace-payments requires pending > 0
A4: Stake blocked if EchoScore < min | B4: 1 | C4: honest block | D4: not simulated | E4: requires fork to measure state
A5: Campaign claim fails with invalid proof | B5: 2 | C5: honest block | D5: not simulated | E5: requires fork + merkle fixture

Sheet Checklist
A1: Checklist Item | B1: Why | C1: Owner | D1: Status
A2: Seed reward campaign funding | B2: Claims fail without funding | C2: treasury/operator | D2: open
A3: Fund staking participants | B3: Stake requires token balance | C3: operator | D3: open
A4: Set treasury payout addresses | B4: Revenue routing | C4: admin | D4: open
A5: Confirm marketplace pause flags | B5: Purchases/withdrawals block when paused | C5: operator | D5: open
A6: Pre-create vesting schedules | B6: Release fails without schedule | C6: admin | D6: open

Sheet Risks
A1: Risk | B1: Impact | C1: Mitigation
A2: Fork simulation blocked locally | B2: No on-chain tx receipts for economic flows | C2: Run fork on supported environment or upgrade system proxy stack
A3: Reward claims fail due to funding | B3: User rewards blocked | C3: Fund campaigns before go-live; alert on low balances
A4: Pending payouts accumulate without sweep | B4: Seller/treasury cashflow stalls | C4: Schedule payout sweeps; monitor pending
A5: Vesting cliff delays releases | B5: Perceived payout delay | C5: Surface cliff schedule in UI

Sheet Meta
A1: Generated | B1: 2026-03-16T02:48:52.925421Z
A2: Model Version | B2: 1.0
A3: Fork Status | B3: blocked: system-configuration NULL object crash
